{
 "device": "phone",
 "viewport": {
  "width": 390,
  "height": 844
 },
 "overlay": true,
 "journeys": {
  "01-focus-cycle": {
   "t0": 1784460082691,
   "events": [
    {
     "t": 979,
     "kind": "nav",
     "label": "/"
    },
    {
     "t": 981,
     "kind": "manual",
     "label": "grant notification permission",
     "mode": "staged"
    },
    {
     "t": 2736,
     "kind": "assert",
     "status": "PASS",
     "label": "idle timer shows the full 25:00 focus block"
    },
    {
     "t": 2741,
     "kind": "assert",
     "status": "PASS",
     "label": "mode chip reads Focus"
    },
    {
     "t": 2744,
     "kind": "assert",
     "status": "PASS",
     "label": "primary control offers Start"
    },
    {
     "t": 3274,
     "kind": "shot",
     "label": "idle-focus"
    },
    {
     "t": 3789,
     "kind": "nav",
     "label": "fast cycle · ?focus=4&break=3"
    },
    {
     "t": 3842,
     "kind": "tap",
     "x": 259.9375,
     "y": 515.09375,
     "label": "Start"
    },
    {
     "t": 5477,
     "kind": "wait",
     "label": "wedge draining"
    },
    {
     "t": 5485,
     "kind": "assert",
     "status": "PASS",
     "label": "running: control flips to Pause"
    },
    {
     "t": 5488,
     "kind": "assert",
     "status": "PASS",
     "label": "running: wedge is draining (time below 00:04)"
    },
    {
     "t": 6012,
     "kind": "shot",
     "label": "focus-running"
    },
    {
     "t": 9517,
     "kind": "wait",
     "label": "block completes"
    },
    {
     "t": 9521,
     "kind": "assert",
     "status": "PASS",
     "label": "completion hands off to Break automatically"
    },
    {
     "t": 9525,
     "kind": "assert",
     "status": "PASS",
     "label": "break block queued at full 00:03"
    },
    {
     "t": 10062,
     "kind": "shot",
     "label": "break-queued"
    }
   ],
   "net": [
    {
     "t": 35,
     "method": "GET",
     "url": "/",
     "status": 200,
     "type": "document"
    },
    {
     "t": 226,
     "method": "GET",
     "url": "https://fonts.googleapis.com/css2?family=Archivo:wght@500;800&family=Space+Grotesk:wght@400;600&display=swap",
     "status": 200,
     "type": "stylesheet"
    },
    {
     "t": 477,
     "method": "GET",
     "url": "https://fonts.gstatic.com/s/spacegrotesk/v22/V8mDoQDjQSkFtoMM3T6r8E7mPbF4C_k3HqU.woff2",
     "status": 200,
     "type": "font"
    },
    {
     "t": 478,
     "method": "GET",
     "url": "https://fonts.gstatic.com/s/archivo/v25/k3kPo8UDI-1M0wlSV9XAw6lQkqWY8Q82sLydOxKsv4Rn.woff2",
     "status": 200,
     "type": "font"
    },
    {
     "t": 3279,
     "method": "GET",
     "url": "/?focus=4&break=3",
     "status": 200,
     "type": "document"
    },
    {
     "t": 3286,
     "method": "GET",
     "url": "https://fonts.googleapis.com/css2?family=Archivo:wght@500;800&family=Space+Grotesk:wght@400;600&display=swap",
     "status": 200,
     "type": "stylesheet"
    },
    {
     "t": 3289,
     "method": "GET",
     "url": "https://fonts.gstatic.com/s/archivo/v25/k3kPo8UDI-1M0wlSV9XAw6lQkqWY8Q82sLydOxKsv4Rn.woff2",
     "status": 200,
     "type": "font"
    },
    {
     "t": 3289,
     "method": "GET",
     "url": "https://fonts.gstatic.com/s/spacegrotesk/v22/V8mDoQDjQSkFtoMM3T6r8E7mPbF4C_k3HqU.woff2",
     "status": 200,
     "type": "font"
    }
   ],
   "video": "videos/01-focus-cycle.webm"
  },
  "02-pause-resume": {
   "t0": 1784460093002,
   "events": [
    {
     "t": 860,
     "kind": "nav",
     "label": "/?focus=60"
    },
    {
     "t": 923,
     "kind": "tap",
     "x": 259.9375,
     "y": 515.09375,
     "label": "Start"
    },
    {
     "t": 3171,
     "kind": "wait",
     "label": "counting down"
    },
    {
     "t": 3184,
     "kind": "tap",
     "x": 259.9375,
     "y": 515.09375,
     "label": "Pause"
    },
    {
     "t": 4818,
     "kind": "wait",
     "label": "holding while paused"
    },
    {
     "t": 4824,
     "kind": "assert",
     "status": "PASS",
     "label": "paused time does not move"
    },
    {
     "t": 4827,
     "kind": "assert",
     "status": "PASS",
     "label": "control offers Resume while paused"
    },
    {
     "t": 5343,
     "kind": "shot",
     "label": "paused"
    },
    {
     "t": 5354,
     "kind": "tap",
     "x": 259.9375,
     "y": 515.09375,
     "label": "Resume"
    },
    {
     "t": 6895,
     "kind": "wait",
     "label": "countdown resumes"
    },
    {
     "t": 6898,
     "kind": "assert",
     "status": "PASS",
     "label": "resume continues the countdown"
    },
    {
     "t": 7433,
     "kind": "shot",
     "label": "resumed"
    }
   ],
   "net": [
    {
     "t": 9,
     "method": "GET",
     "url": "/?focus=60",
     "status": 200,
     "type": "document"
    },
    {
     "t": 131,
     "method": "GET",
     "url": "https://fonts.googleapis.com/css2?family=Archivo:wght@500;800&family=Space+Grotesk:wght@400;600&display=swap",
     "status": 200,
     "type": "stylesheet"
    },
    {
     "t": 339,
     "method": "GET",
     "url": "https://fonts.gstatic.com/s/spacegrotesk/v22/V8mDoQDjQSkFtoMM3T6r8E7mPbF4C_k3HqU.woff2",
     "status": 200,
     "type": "font"
    },
    {
     "t": 357,
     "method": "GET",
     "url": "https://fonts.gstatic.com/s/archivo/v25/k3kPo8UDI-1M0wlSV9XAw6lQkqWY8Q82sLydOxKsv4Rn.woff2",
     "status": 200,
     "type": "font"
    }
   ],
   "video": "videos/02-pause-resume.webm"
  },
  "03-slices-persist": {
   "t0": 1784460100608,
   "events": [
    {
     "t": 794,
     "kind": "nav",
     "label": "/?focus=3&break=2"
    },
    {
     "t": 838,
     "kind": "assert",
     "status": "PASS",
     "label": "empty state invites the first block"
    },
    {
     "t": 871,
     "kind": "tap",
     "x": 259.9375,
     "y": 515.09375,
     "label": "Start"
    },
    {
     "t": 5092,
     "kind": "wait",
     "label": "block completes"
    },
    {
     "t": 5095,
     "kind": "assert",
     "status": "PASS",
     "label": "one slice earned after completing a block"
    },
    {
     "t": 5634,
     "kind": "shot",
     "label": "one-slice-earned"
    },
    {
     "t": 6145,
     "kind": "nav",
     "label": "reload"
    },
    {
     "t": 6162,
     "kind": "assert",
     "status": "PASS",
     "label": "the earned slice survives a reload"
    },
    {
     "t": 6166,
     "kind": "assert",
     "status": "PASS",
     "label": "empty-state prompt stays gone"
    },
    {
     "t": 6682,
     "kind": "shot",
     "label": "slice-persists-after-reload"
    }
   ],
   "net": [
    {
     "t": 7,
     "method": "GET",
     "url": "/?focus=3&break=2",
     "status": 200,
     "type": "document"
    },
    {
     "t": 112,
     "method": "GET",
     "url": "https://fonts.googleapis.com/css2?family=Archivo:wght@500;800&family=Space+Grotesk:wght@400;600&display=swap",
     "status": 200,
     "type": "stylesheet"
    },
    {
     "t": 275,
     "method": "GET",
     "url": "https://fonts.gstatic.com/s/spacegrotesk/v22/V8mDoQDjQSkFtoMM3T6r8E7mPbF4C_k3HqU.woff2",
     "status": 200,
     "type": "font"
    },
    {
     "t": 293,
     "method": "GET",
     "url": "https://fonts.gstatic.com/s/archivo/v25/k3kPo8UDI-1M0wlSV9XAw6lQkqWY8Q82sLydOxKsv4Rn.woff2",
     "status": 200,
     "type": "font"
    },
    {
     "t": 5637,
     "method": "GET",
     "url": "/?focus=3&break=2",
     "status": 200,
     "type": "document"
    },
    {
     "t": 5642,
     "method": "GET",
     "url": "https://fonts.googleapis.com/css2?family=Archivo:wght@500;800&family=Space+Grotesk:wght@400;600&display=swap",
     "status": 200,
     "type": "stylesheet"
    },
    {
     "t": 5644,
     "method": "GET",
     "url": "https://fonts.gstatic.com/s/archivo/v25/k3kPo8UDI-1M0wlSV9XAw6lQkqWY8Q82sLydOxKsv4Rn.woff2",
     "status": 200,
     "type": "font"
    },
    {
     "t": 5644,
     "method": "GET",
     "url": "https://fonts.gstatic.com/s/spacegrotesk/v22/V8mDoQDjQSkFtoMM3T6r8E7mPbF4C_k3HqU.woff2",
     "status": 200,
     "type": "font"
    }
   ],
   "video": "videos/03-slices-persist.webm"
  },
  "04-reset-no-credit": {
   "t0": 1784460107452,
   "events": [
    {
     "t": 826,
     "kind": "nav",
     "label": "/?focus=60"
    },
    {
     "t": 893,
     "kind": "tap",
     "x": 259.9375,
     "y": 515.09375,
     "label": "Start"
    },
    {
     "t": 3434,
     "kind": "wait",
     "label": "mid-block"
    },
    {
     "t": 3446,
     "kind": "tap",
     "x": 93.9375,
     "y": 515.09375,
     "label": "Reset"
    },
    {
     "t": 3740,
     "kind": "assert",
     "status": "PASS",
     "label": "reset restores the full block"
    },
    {
     "t": 3742,
     "kind": "assert",
     "status": "PASS",
     "label": "control returns to Start"
    },
    {
     "t": 3744,
     "kind": "assert",
     "status": "PASS",
     "label": "no slice awarded for an abandoned block"
    },
    {
     "t": 4314,
     "kind": "shot",
     "label": "reset-full-block"
    }
   ],
   "net": [
    {
     "t": 7,
     "method": "GET",
     "url": "/?focus=60",
     "status": 200,
     "type": "document"
    },
    {
     "t": 125,
     "method": "GET",
     "url": "https://fonts.googleapis.com/css2?family=Archivo:wght@500;800&family=Space+Grotesk:wght@400;600&display=swap",
     "status": 200,
     "type": "stylesheet"
    },
    {
     "t": 311,
     "method": "GET",
     "url": "https://fonts.gstatic.com/s/archivo/v25/k3kPo8UDI-1M0wlSV9XAw6lQkqWY8Q82sLydOxKsv4Rn.woff2",
     "status": 200,
     "type": "font"
    },
    {
     "t": 326,
     "method": "GET",
     "url": "https://fonts.gstatic.com/s/spacegrotesk/v22/V8mDoQDjQSkFtoMM3T6r8E7mPbF4C_k3HqU.woff2",
     "status": 200,
     "type": "font"
    }
   ],
   "video": "videos/04-reset-no-credit.webm"
  }
 }
}